{
  "client.dll": {
    "dwEntityList": 107868808,
    "dwGameEntitySystem": 107868808,
    "dwGameEntitySystem_highestEntityIndex": 8336,
    "dwGlobalVars": 97109200,
    "dwLocalPlayerPawn": 97154808,
    "dwPrediction": 97154592,
    "dwSensitivity": 104355992,
    "dwSensitivity_sensitivity": 88,
    "dwViewMatrix": 104387792,
    "dwViewRender": 104385464
  },
  "engine2.dll": {
    "dwBuildNumber": 6360228,
    "dwNetworkGameClient": 9495808,
    "dwNetworkGameClient_clientTickCount": 888,
    "dwNetworkGameClient_deltaTick": 588,
    "dwNetworkGameClient_isBackgroundMap": 2888735,
    "dwNetworkGameClient_localPlayer": 248,
    "dwNetworkGameClient_maxClients": 576,
    "dwNetworkGameClient_serverTickCount": 588,
    "dwNetworkGameClient_signOnState": 560,
    "dwWindowHeight": 9513180,
    "dwWindowWidth": 9513176
  },
  "inputsystem.dll": {
    "dwInputSystem": 273232
  },
  "panorama.dll": {},
  "soundsystem.dll": {
    "dwSoundSystem": 5321632,
    "dwSoundSystem_engineViewData": 124
  }
}